dovpanda/__init__.py
dovpanda/base.py
dovpanda/config.py
dovpanda/core.py
dovpanda/tips.py
dovpanda/resource/logo
dovpanda/tip_files/many_cols_csv.html
dovpanda/tip_files/map_with_dict.html
dovpanda/tip_files/read_csv_header_skiprows.html
dovpanda/tip_files/readable_loc_iloc.html
dovpanda/tip_files/resample.html
dovpanda-0.0.5.dist-info/AUTHORS.rst
dovpanda-0.0.5.dist-info/LICENSE
dovpanda-0.0.5.dist-info/METADATA
dovpanda-0.0.5.dist-info/WHEEL
dovpanda-0.0.5.dist-info/top_level.txt
dovpanda-0.0.5.dist-info/RECORD
