Metadata-Version: 2.1
Name: dovpanda
Version: 0.0.5
Summary: Directions overlay for working with pandas in an analysis environment
Home-page: https://github.com/dovpanda-dev/dovpanda
Author: Dean Langsam
Author-email: deanla@gmail.com
License: UNKNOWN
Platform: UNKNOWN
Classifier: Development Status :: 2 - Pre-Alpha
Classifier: License :: OSI Approved :: BSD License
Classifier: Operating System :: OS Independent
Classifier: Programming Language :: Python :: 3 :: Only
Classifier: Programming Language :: Python :: 3.6
Classifier: Programming Language :: Python :: 3.7
Requires-Python: >=3.6
Requires-Dist: pandas
